aus_local_councils/__init__.py
aus_local_councils/nsw.py
aus_local_councils/nt.py
aus_local_councils/qld.py
aus_local_councils/sa.py
aus_local_councils/tas.py
aus_local_councils/vic.py
aus_local_councils/wa.py
aus_local_councils-1.1.dist-info/METADATA
aus_local_councils-1.1.dist-info/WHEEL
aus_local_councils-1.1.dist-info/top_level.txt
aus_local_councils-1.1.dist-info/RECORD
