Metadata-Version: 2.1
Name: aus-local-councils
Version: 1.1
Summary: Get list of local councils for Australian states/territories.
Home-page: https://github.com/OpenGovAus/aus-local-councils
Author: king-millez
Author-email: millez.dev@gmail.com
License: UNKNOWN
Platform: UNKNOWN
Classifier: Programming Language :: Python :: 3
Classifier: Operating System :: OS Independent
Requires-Python: >=3.6
